numberConverter_porfanid/__init__.py
numberConverter_porfanid/numberConverter.py
numberConverter_porfanid-0.1.0.dist-info/LICENSE
numberConverter_porfanid-0.1.0.dist-info/METADATA
numberConverter_porfanid-0.1.0.dist-info/WHEEL
numberConverter_porfanid-0.1.0.dist-info/top_level.txt
numberConverter_porfanid-0.1.0.dist-info/RECORD
